{
  "weekday": {
    "1": {
      "morning": ["吳立偉 院長", "郭芷毓 醫師"],
      "afternoon": ["林峻豪 副院長"],
      "night": ["林峻豪 副院長"]
    },
    "2": {
      "morning": ["林峻豪 副院長"],
      "afternoon": ["郭芷毓 醫師"],
      "night": ["吳立偉 院長", "郭芷毓 醫師"]
    },
    "3": {
      "morning": ["吳立偉 院長", "郭芷毓 醫師"],
      "afternoon": ["黃俞華 副院長"],
      "night": ["黃俞華 副院長"]
    },
    "4": {
      "morning": ["吳立偉 院長"],
      "afternoon": ["林峻豪 副院長"],
      "night": ["林峻豪 副院長"]
    },
    "5": {
      "morning": ["林峻豪 副院長"],
      "afternoon": ["郭芷毓 醫師"],
      "night": ["郭芷毓 醫師"]
    }
  },

  "saturday": {
    "cycle": [
      { "date": "2025-12-06", "doctor": "劉俊良 醫師" },
      { "date": "2025-12-13", "doctor": "林峻豪 副院長" },
      { "date": "2025-12-20", "doctor": "劉俊良 醫師" },
      { "date": "2025-12-27", "doctor": "林峻豪 副院長" }
    ],
    "sections": {
      "morning": ["早診（08:00–12:00）"],
      "afternoon": ["午診（14:30–17:00）"]
    }
  },

  "sunday": {
    "closed": true
  }
}
